{
    "forClass": "DataSource",
    "revision": "7f159ecc-78b3-44c3-8518-b1f96b1e5104",
    "schema": {
        "properties": {
            "name": {
                "type": "string"
            },
            "tags": {
                "items": {
                    "type": "string"
                },
                "type": "array"
            },
            "uri": {
                "type": "string"
            }
        },
        "required": [
            "name"
        ],
        "type": "object"
    },
    "version": 1
}